README
setup.py
django_model_versions.egg-info/PKG-INFO
django_model_versions.egg-info/SOURCES.txt
django_model_versions.egg-info/dependency_links.txt
django_model_versions.egg-info/top_level.txt
modelversions/__init__.py
modelversions/models.py
modelversions/tests.py