Metadata-Version: 1.1
Name: django-model-versions
Version: 0.4.0
Summary: A base model class for adding version information and preventing concurrent modifications
Home-page: https://github.com/colinhowe/django-model-versions
Author: Colin Howe
Author-email: colin@colinhowe.co.uk
License: Apache 2.0
Platform: UNKNOWN
Classifier: Development Status :: 4 - Beta
Classifier: Environment :: Web Environment
Classifier: Framework :: Django
Classifier: Intended Audience :: Developers
Classifier: License :: OSI Approved :: Apache Software License
Classifier: Operating System :: OS Independent
Classifier: Programming Language :: Python
Classifier: Topic :: Software Development :: Libraries :: Python Modules
